mkdocs/__init__.py
mkdocs/__main__.py
mkdocs/exceptions.py
mkdocs/localization.py
mkdocs/plugins.py
mkdocs/py.typed
mkdocs/theme.py
mkdocs/commands/__init__.py
mkdocs/commands/build.py
mkdocs/commands/get_deps.py
mkdocs/commands/gh_deploy.py
mkdocs/commands/new.py
mkdocs/commands/serve.py
mkdocs/config/__init__.py
mkdocs/config/base.py
mkdocs/config/config_options.py
mkdocs/config/defaults.py
mkdocs/contrib/__init__.py
mkdocs/contrib/search/__init__.py
mkdocs/contrib/search/prebuild-index.js
mkdocs/contrib/search/search_index.py
mkdocs/contrib/search/lunr-language/lunr.ar.js
mkdocs/contrib/search/lunr-language/lunr.da.js
mkdocs/contrib/search/lunr-language/lunr.de.js
mkdocs/contrib/search/lunr-language/lunr.du.js
mkdocs/contrib/search/lunr-language/lunr.es.js
mkdocs/contrib/search/lunr-language/lunr.fi.js
mkdocs/contrib/search/lunr-language/lunr.fr.js
mkdocs/contrib/search/lunr-language/lunr.hu.js
mkdocs/contrib/search/lunr-language/lunr.it.js
mkdocs/contrib/search/lunr-language/lunr.ja.js
mkdocs/contrib/search/lunr-language/lunr.jp.js
mkdocs/contrib/search/lunr-language/lunr.multi.js
mkdocs/contrib/search/lunr-language/lunr.nl.js
mkdocs/contrib/search/lunr-language/lunr.no.js
mkdocs/contrib/search/lunr-language/lunr.pt.js
mkdocs/contrib/search/lunr-language/lunr.ro.js
mkdocs/contrib/search/lunr-language/lunr.ru.js
mkdocs/contrib/search/lunr-language/lunr.stemmer.support.js
mkdocs/contrib/search/lunr-language/lunr.sv.js
mkdocs/contrib/search/lunr-language/lunr.th.js
mkdocs/contrib/search/lunr-language/lunr.tr.js
mkdocs/contrib/search/lunr-language/lunr.vi.js
mkdocs/contrib/search/lunr-language/tinyseg.js
mkdocs/contrib/search/templates/search/lunr.js
mkdocs/contrib/search/templates/search/main.js
mkdocs/contrib/search/templates/search/worker.js
mkdocs/livereload/__init__.py
mkdocs/structure/__init__.py
mkdocs/structure/files.py
mkdocs/structure/nav.py
mkdocs/structure/pages.py
mkdocs/structure/toc.py
mkdocs/templates/sitemap.xml
mkdocs/tests/__init__.py
mkdocs-1.5.0.dist-info/METADATA
mkdocs-1.5.0.dist-info/WHEEL
mkdocs-1.5.0.dist-info/entry_points.txt
mkdocs-1.5.0.dist-info/licenses/LICENSE
mkdocs-1.5.0.dist-info/RECORD
